superweather/__init__.py
superweather/main.py
superweather-0.5.dist-info/METADATA
superweather-0.5.dist-info/WHEEL
superweather-0.5.dist-info/entry_points.txt
superweather-0.5.dist-info/top_level.txt
superweather-0.5.dist-info/RECORD
