Metadata-Version: 2.4
Name: superweather
Version: 0.5
Summary: A package to fetch and display air quality data.
Home-page: https://github.com/shabakhti
Author: Mohammad Shabakhti
Author-email: smmshabakhti@gmail.com
Classifier: Programming Language :: Python :: 3
Classifier: License :: OSI Approved :: MIT License
Classifier: Operating System :: OS Independent
Requires-Python: >=3.7
Requires-Dist: requests
Requires-Dist: pyttsx3
Dynamic: author
Dynamic: author-email
Dynamic: classifier
Dynamic: description
Dynamic: description-content-type
Dynamic: home-page
Dynamic: requires-dist
Dynamic: requires-python
Dynamic: summary
